[
  {
    "id": 1,
    "name": "Bella",
    "email": "bella@yopmail.com",
    "age": 33,
    "gender": "female",
    "ethnicity": "african-american",
    "points": 0,
    "goals": {
      "exercise": 150,
      "mindfulness": 2,
      "sleep": 7,
      "fruitsAndVeggies": 5,
      "water": 70,
      "selfCheck": 1,
      "mammogram": 1
    },
    "friendsWith": [
      {
        "name": "Juliana",
        "id": 2
      },
      {
        "name": "Angie",
        "id": 3
      }
    ],
    "dashboardTip": [{
      "title": "Get to know your boobs",
      "text": "The best way to know your normal is by taking a look every month. We’ll walk you through the process. Every month makes a difference!",
      "link": "/library/breast-health?view=self-check"
    }],
    "exerciseTip": [{
      "title": "It looks like you’re having trouble keeping up with your exercise routine this week.",
      "text": "We’ve got your back. Check out our tips on how to incorporate mini workouts into your day.",
      "link": "/library/exercise?view=tips"
    }],
    "mindfulnessTip": [{
      "title": "It’s more than just OOOOMMMM.",
      "text": "Adding a practice of mindfulness can increase your concentration, reduce anxiety and stress, and even improve your eating habits.",
      "link": "/library/mindfulness?view=tips"
    }],
    "waterTip": [{
      "title": "Did you know? Up to 60% of the human adult body is water.",
      "text": "Dehydration can us feel rotten. Check out our tips on how to add more water to your day to day",
      "link": "/library/healthy-eating?view=tips"
    }],
    "fruitsAndVeggiesTip": [{
      "title": "Hmm, haven't been eating your broccolis lately?",
      "text": "A diet rich in vegetables and fruits can lower blood pressure, reduce the risk of heart disease and stroke, prevent some types of cancer. Check out how you can incoporate more greens in your diet.",
      "link": "/library/healthy-eating?view=tips"
    }],
    "sleepTip": [{
      "title": "Need some tips to get more ZZZs?",
      "text": "Try setting the mood by keeping your room dark and quiet. Check out the library for more tips.",
      "link": "/library/sleep?view=tips"
    }],
    "selfCheckTip": [{
      "title": "Get to know your boobs",
      "text": "The best way to know your normal is by taking a look every month. We’ll walk you through the process. Every month makes a difference!",
      "link": "/library/breast-health?view=self-check"
    }],
    "mammogramTip": [{
      "title": "When's the right time to get a MAMMOGRAM?",
      "text": "We are glad you asked! Find out here!",
      "link": "/library/breast-health?view=mammogram"
    }],
    "doneSelfCheckThisMonth": false,
    "scheduledMammogram": false,
    "previousSelfCheckNotes": [],
    "previousMammogramNotes": [],
    "data": [
      {
        "date": "09/24/2020",
        "exercise": 0,
        "mindfulness": 0,
        "sleep": 0,
        "water": 0,
        "fruitsAndVeggies": 1,
        "selfCheck": 0,
        "mammogram": 0
      }
    ],
    "weeklyData": [
      {
        "date": "yesterday",
        "exercise": 0,
        "exercises": [],
        "mindfulness": 0,
        "sleep": 6,
        "water": 44,
        "fruitsAndVeggies": 2,
        "selfCheck": 0,
        "mammogram": 0
      },      
      {
        "date": "twoDaysAgo",
        "exercise": 0,
        "exercises": [],
        "mindfulness": 1,
        "sleep": 5,
        "water": 55,
        "fruitsAndVeggies": 1,
        "selfCheck": 0,
        "mammogram": 0
      },
      {
        "date": "threeDaysAgo",
        "exercise": 0,
        "exercises": [],
        "mindfulness": 0,
        "sleep": 6,
        "water": 48,
        "fruitsAndVeggies": 3,
        "selfCheck": 0,
        "mammogram": 0
      },
      {
        "date": "fourDaysAgo",
        "exercise": 10,
        "exercises": [
          {
            "activity": "Walk",
            "duration": 10
          }
        ],
        "mindfulness": 0,
        "sleep": 4,
        "water": 56,
        "fruitsAndVeggies": 3,
        "selfCheck": 0,
        "mammogram": 0
      },
      {
        "date": "fiveDaysAgo",
        "exercise": 0,
        "exercises": [],
        "mindfulness": 0,
        "sleep": 5,
        "water": 64,
        "fruitsAndVeggies": 3,
        "selfCheck": 0,
        "mammogram": 0
      },
      {
        "date": "sixDaysAgo",
        "exercise": 0,
        "exercises": [],
        "mindfulness": 0,
        "sleep": 5,
        "water": 61,
        "fruitsAndVeggies": 3,
        "selfCheck": 0,
        "mammogram": 0
      },
      {
        "date": "sevenDaysAgo",
        "exercise": 0,
        "exercises": [],
        "mindfulness": 0,
        "sleep": 6,
        "water": 69,
        "fruitsAndVeggies": 3,
        "selfCheck": 0,
        "mammogram": 0
      }
    ]
  },
  {
    "id": 2,
    "name": "Juliana",
    "email": "juliana@yopmail.com",
    "age": 36,
    "gender": "female",
    "ethnicity": "hispanic",
    "points": 2489,
    "goals": {
      "exercise": 400,
      "mindfulness": 7,
      "sleep": 8,
      "fruitsAndVeggies": 5,
      "water": 100,
      "selfCheck": 1,
      "mammogram": 1
    },
    "friendsWith": [
      {
        "name": "Bella",
        "id": 1
      },
      {
        "name": "Angie",
        "id": 3
      }
    ],
    "dashboardTip": [{
      "title": "Need some tips to get more ZZZs? ",
      "text": "Try setting the mood by keeping your room dark and quiet. Check out the library for more tips.",
      "link": "/library/sleep?view=tips"
    }],
    "exerciseTip": [{
      "title": "Whoa! Way to get that heart rate up every day",
      "text": "Keep up the good work. If you ever need some new workout ideas, check out our library.",
      "link": ""
    }],
    "mindfulnessTip": [{
      "title": "You’re on a roll!",
      "text": "Keep up the good work on makign mindfulness a part of your day. If you need more inspriation, check out our library.",
      "link": ""
    }],
    "waterTip": [{
      "title": "We’re proud of you for getting the recommended amount of water everyday. Keep it up!",
      "text": "Dehydration can us feel rotten. Check out our tips on how to add more water to your day to day",
      "link": ""
    }],
    "fruitsAndVeggiesTip": [{
      "title": "Way to snack!",
      "text": "You’re on a roll with eating fruits and veggies. Keep up the good work. If you ever need more snacking inspiraiton, check out our library.",
      "link": "/library/healthy-eating?view=tips"
    }],
    "sleepTip": [{
      "title": "Need some tips to get more ZZZs?",
      "text": "Try setting the mood by keeping your room dark and quiet. Check out the library for more tips.",
      "link": "/library/sleep?view=tips"
    }],
    "selfCheckTip": [{
      "title": "You know your boobs",
      "text": "Keep up the good work! Help your friends make a monthly shelf check a part of their monthly routine. Send them an encouraging text.",
      "link": ""
    }],
    "mammogramTip": [{
      "title": "When's the right time to get a MAMMOGRAM?",
      "text": "We are glad you asked! Find out here!",
      "link": "/library/breast-health?view=mammogram"
    }],
    "doneSelfCheckThisMonth": false,
    "scheduledMammogram": false,
    "previousSelfCheckNotes": [
      {
        "date": "2020-05-01",
        "content": "Felt a lump?"
      },
      {
        "date": "2020-06-15",
        "content": "Got lump checked out by doc, is benign. Phew."
      },
      {
        "date": "2020-08-01",
        "content": "All good"
      },
      {
        "date": "2020-09-01",
        "content": "Still good! Posted a self-check selfie today and I think I inspired Bella to finally check her girls too! ;)"
      }
    ],
    "previousMammogramNotes": [
      {
        "date": "2019-11-29",
        "content": "Results came back normal."
      }
    ],
    "data": [
      {
        "date": "09/24/2020",
        "exercise": 0,
        "mindfulness": 0,
        "sleep": 0,
        "water": 84,
        "fruitsAndVeggies": 3,
        "selfCheck": 0,
        "mammogram": 0
      }
    ],
    "weeklyData" : [
      {
        "date": "yesterday",
        "exercise": 0,
        "exercises": [],
        "mindfulness": 1,
        "sleep": 7,
        "water": 84,
        "fruitsAndVeggies": 3,
        "selfCheck": 0,
        "mammogram": 0
      },      
      {
        "date": "twoDaysAgo",
        "exercise": 10,
        "exercises": [
          {
            "activity": "Yoga",
            "duration": 10
          }
        ],
        "mindfulness": 1,
        "sleep": 9,
        "water": 100,
        "fruitsAndVeggies": 5,
        "selfCheck": 0,
        "mammogram": 0
      },
      {
        "date": "threeDaysAgo",
        "exercise": 30,
        "exercises": [
          {
            "activity": "Hike",
            "duration": 10
          },
          {
            "activity": "HIIT",
            "duration": 20
          }
        ],
        "mindfulness": 1,
        "sleep": 7,
        "water": 92,
        "fruitsAndVeggies": 6,
        "selfCheck": 0,
        "mammogram": 0
      },
      {
        "date": "fourDaysAgo",
        "exercise": 50,
        "exercises": [
          {
            "activity": "Weights",
            "duration": 30
          },
          {
            "activity": "Walk",
            "duration": 20
          }
        ],
        "mindfulness": 1,
        "sleep": 9,
        "water": 120,
        "fruitsAndVeggies": 4,
        "selfCheck": 0,
        "mammogram": 0
      },
      {
        "date": "fiveDaysAgo",
        "exercise": 100,
        "exercises": [
          {
            "activity": "Run",
            "duration": 30
          },
          {
            "activity": "Walk",
            "duration": 20
          },
          {
            "activity": "HIIT",
            "duration": 50
          }
        ],
        "mindfulness": 1,
        "sleep": 8,
        "water": 70,
        "fruitsAndVeggies": 3,
        "selfCheck": 0,
        "mammogram": 0
      },
      {
        "date": "sixDaysAgo",
        "exercise": 120,
        "exercises": [
          {
            "activity": "Hike",
            "duration": 120
          }
        ],
        "mindfulness": 1,
        "sleep": 6,
        "water": 110,
        "fruitsAndVeggies": 4,
        "selfCheck": 0,
        "mammogram": 0
      },
      {
        "date": "sevenDaysAgo",
        "exercise": 30,
        "exercises": [
          {
            "activity": "Yoga",
            "duration": 30
          }
        ],
        "mindfulness": 1,
        "sleep": 8,
        "water": 102,
        "fruitsAndVeggies": 5,
        "selfCheck": 0,
        "mammogram": 0
      }
    ]
  },
  {
    "id": 3,
    "name": "Angie",
    "email": "Angieobo@yopmail.com",
    "age": 39,
    "gender": "female",
    "ethnicity": "white",
    "points": 990,
    "goals": {
      "exercise": 180,
      "mindfulness": 0,
      "sleep": 7,
      "fruitsAndVeggies": 5,
      "water": 50,
      "selfCheck": 1,
      "mammogram": 1
    },
    "friendsWith": [
      {
        "name": "Bella",
        "id": 1
      },
      {
        "name": "Juliana",
        "id": 2
      }
    ],
    "dashboardTip": [{
      "title": "Looks like you haven't scheduled a mammogram yet for this year. Not sure where to start? We got you!",
      "text": "Head to our help section to learn more about setting up an appointment.",
      "link": "/library/breast-health?view=mammogram"
    }],
    "exerciseTip": [{
      "title": "It looks like you’re having trouble keeping up with your exercise routine this week.",
      "text": "We’ve got your back. Check out our tips on how to incorporate mini workouts into your day.",
      "link": "/library/exercise?view=tips"
    }],
    "mindfulnessTip": [{
      "title": "It’s more than just OOOOMMMM.",
      "text": "Adding a practice of mindfulness can increase your concentration, reduce anxiety and stress, and even improve your eating habits.",
      "link": "/library/mindfulness?view=tips"
    }],
    "waterTip": [{
      "title": "Did you know? Up to 60% of the human adult body is water.",
      "text": "Dehydration can us feel rotten. Check out our tips on how to add more water to your day to day",
      "link": "/library/healthy-eating?view=tips"
    }],
    "fruitsAndVeggiesTip": [{
      "title": "Hmm, haven't been eating your broccolis lately?",
      "text": "A diet rich in vegetables and fruits can lower blood pressure, reduce the risk of heart disease and stroke, prevent some types of cancer. Check out how you can incoporate more greens in your diet.",
      "link": "/library/healthy-eating?view=tips"
    }],
    "sleepTip": [{
      "title": "Need some tips to get more ZZZs?",
      "text": "Try setting the mood by keeping your room dark and quiet. Check out the library for more tips.",
      "link": "/library/sleep?view=tips"
    }],
    "selfCheckTip": [{
      "title": "Get to know your boobs",
      "text": "The best way to know your normal is by taking a look every month. We’ll walk you through the process. Every month makes a difference!",
      "link": "/library/breast-health?view=self-check"
    }],
    "mammogramTip": [{
      "title": "When's the right time to get a MAMMOGRAM?",
      "text": "We are glad you asked! Find out here!",
      "link": "/library/breast-health?view=mammogram"
    }],
    "doneSelfCheckThisMonth": false,
    "scheduledMammogram": false,
    "previousSelfCheckNotes": [
      {
        "date": "2020-05-27",
        "content": "Felt sore. Might just be workout"
      },
      {
        "date": "2020-08-27",
        "content": "That wasn't too bad."
      }
    ],
    "previousMammogramNotes": [],
    "data": [
      {
        "date": "09/24/2020",
        "exercise": 0,
        "mindfulness": 0,
        "sleep": 0,
        "water": 10,
        "fruitsAndVeggies": 1,
        "selfCheck": 0,
        "mammogram": 0
      }
    ],
    "weeklyData": [
      {
        "date": "yesterday",
        "exercise": 0,
        "exercises": [],
        "mindfulness": 0,
        "sleep": 5,
        "water": 75,
        "fruitsAndVeggies": 1,
        "selfCheck": 0,
        "mammogram": 0
      },
      {
        "date": "twoDaysAgo",
        "exercise": 0,
        "exercises": [],
        "mindfulness": 0,
        "sleep": 3,
        "water": 49,
        "fruitsAndVeggies": 3,
        "selfCheck": 0,
        "mammogram": 0
      },
      {
        "date": "threeDaysAgo",
        "exercise": 10,
        "exercises": [
          {
            "activity": "Walk",
            "duration": 10
          }
        ],
        "mindfulness": 0,
        "sleep": 5,
        "water": 75,
        "fruitsAndVeggies": 3,
        "selfCheck": 0,
        "mammogram": 0
      },
      {
        "date": "fourDaysAgo",
        "exercise": 0,
        "exercises": [],
        "mindfulness": 0,
        "sleep": 5,
        "water": 45,
        "fruitsAndVeggies": 3,
        "selfCheck": 0,
        "mammogram": 0
      },
      {
        "date": "fiveDaysAgo",
        "exercise": 20,
        "exercises": [
          {
            "activity": "HIIT",
            "duration": 20
          }
        ],
        "mindfulness": 0,
        "sleep": 4,
        "water": 67,
        "fruitsAndVeggies": 3,
        "selfCheck": 0,
        "mammogram": 0
      },
      {
        "date": "sixDaysAgo",
        "exercise": 0,
        "exercises": [],
        "mindfulness": 0,
        "sleep": 4,
        "water": 55,
        "fruitsAndVeggies": 3,
        "selfCheck": 0,
        "mammogram": 0
      },
      {
        "date": "sevenDaysAgo",
        "exercise": 0,
        "exercises": [],
        "mindfulness": 0,
        "sleep": 5,
        "water": 48,
        "fruitsAndVeggies": 3,
        "selfCheck": 0,
        "mammogram": 0
      }
    ]
  }
]